{
    "description": "",
    "tags": [
        {
            "id": 15717451,
            "tagId": 29531,
            "name": "age",
            "value": 4,
            "labelerLogin": "cx@datasetninja.com",
            "createdAt": "2024-01-19T09:24:54.754Z",
            "updatedAt": "2024-01-19T09:24:54.754Z"
        },
        {
            "id": 15717452,
            "tagId": 29532,
            "name": "datetime",
            "value": "2021-05-22",
            "labelerLogin": "cx@datasetninja.com",
            "createdAt": "2024-01-19T09:24:54.754Z",
            "updatedAt": "2024-01-19T09:24:54.754Z"
        },
        {
            "id": 15717453,
            "tagId": 29533,
            "name": "district",
            "value": "Lira",
            "labelerLogin": "cx@datasetninja.com",
            "createdAt": "2024-01-19T09:24:54.754Z",
            "updatedAt": "2024-01-19T09:24:54.754Z"
        },
        {
            "id": 15717454,
            "tagId": 29535,
            "name": "mlb",
            "value": null,
            "labelerLogin": "cx@datasetninja.com",
            "createdAt": "2024-01-19T09:24:54.754Z",
            "updatedAt": "2024-01-19T09:24:54.754Z"
        },
        {
            "id": 15717455,
            "tagId": 29537,
            "name": "subcounty",
            "value": "Central",
            "labelerLogin": "cx@datasetninja.com",
            "createdAt": "2024-01-19T09:24:54.754Z",
            "updatedAt": "2024-01-19T09:24:54.754Z"
        },
        {
            "id": 15717456,
            "tagId": 29538,
            "name": "variety",
            "value": "LOCAL",
            "labelerLogin": "cx@datasetninja.com",
            "createdAt": "2024-01-19T09:24:54.754Z",
            "updatedAt": "2024-01-19T09:24:54.754Z"
        }
    ],
    "size": {
        "height": 768,
        "width": 1024
    },
    "objects": [
        {
            "id": 128811049,
            "classId": 6511799,
            "objectId": null,
            "description": "",
            "geometryType": "rectangle",
            "labelerLogin": "cx@datasetninja.com",
            "createdAt": "2023-12-17T03:11:10.922Z",
            "updatedAt": "2023-12-17T03:11:10.922Z",
            "tags": [],
            "classTitle": "maize leaf blight",
            "points": {
                "exterior": [
                    [
                        3,
                        12
                    ],
                    [
                        1021,
                        761
                    ]
                ],
                "interior": []
            }
        }
    ]
}