{
    "description": "",
    "tags": [
        {
            "id": 15698836,
            "tagId": 29531,
            "name": "age",
            "value": 4,
            "labelerLogin": "cx@datasetninja.com",
            "createdAt": "2024-01-19T09:24:03.325Z",
            "updatedAt": "2024-01-19T09:24:03.325Z"
        },
        {
            "id": 15698837,
            "tagId": 29532,
            "name": "datetime",
            "value": "2021-05-22",
            "labelerLogin": "cx@datasetninja.com",
            "createdAt": "2024-01-19T09:24:03.325Z",
            "updatedAt": "2024-01-19T09:24:03.325Z"
        },
        {
            "id": 15698838,
            "tagId": 29533,
            "name": "district",
            "value": "Lira",
            "labelerLogin": "cx@datasetninja.com",
            "createdAt": "2024-01-19T09:24:03.325Z",
            "updatedAt": "2024-01-19T09:24:03.325Z"
        },
        {
            "id": 15698839,
            "tagId": 29535,
            "name": "mlb",
            "value": null,
            "labelerLogin": "cx@datasetninja.com",
            "createdAt": "2024-01-19T09:24:03.325Z",
            "updatedAt": "2024-01-19T09:24:03.325Z"
        },
        {
            "id": 15698840,
            "tagId": 29537,
            "name": "subcounty",
            "value": "Central",
            "labelerLogin": "cx@datasetninja.com",
            "createdAt": "2024-01-19T09:24:03.325Z",
            "updatedAt": "2024-01-19T09:24:03.325Z"
        },
        {
            "id": 15698841,
            "tagId": 29538,
            "name": "variety",
            "value": "LOCAL",
            "labelerLogin": "cx@datasetninja.com",
            "createdAt": "2024-01-19T09:24:03.325Z",
            "updatedAt": "2024-01-19T09:24:03.325Z"
        }
    ],
    "size": {
        "height": 768,
        "width": 1024
    },
    "objects": [
        {
            "id": 128808190,
            "classId": 6511799,
            "objectId": null,
            "description": "",
            "geometryType": "rectangle",
            "labelerLogin": "cx@datasetninja.com",
            "createdAt": "2023-12-17T03:10:29.396Z",
            "updatedAt": "2023-12-17T03:10:29.396Z",
            "tags": [],
            "classTitle": "maize leaf blight",
            "points": {
                "exterior": [
                    [
                        3,
                        1
                    ],
                    [
                        1020,
                        761
                    ]
                ],
                "interior": []
            }
        }
    ]
}