{
    "description": "",
    "tags": [
        {
            "id": 15682770,
            "tagId": 29531,
            "name": "age",
            "value": 2,
            "labelerLogin": "cx@datasetninja.com",
            "createdAt": "2024-01-19T09:23:18.613Z",
            "updatedAt": "2024-01-19T09:23:18.613Z"
        },
        {
            "id": 15682771,
            "tagId": 29532,
            "name": "datetime",
            "value": "2021-05-23",
            "labelerLogin": "cx@datasetninja.com",
            "createdAt": "2024-01-19T09:23:18.613Z",
            "updatedAt": "2024-01-19T09:23:18.613Z"
        },
        {
            "id": 15682772,
            "tagId": 29533,
            "name": "district",
            "value": "Oyam",
            "labelerLogin": "cx@datasetninja.com",
            "createdAt": "2024-01-19T09:23:18.613Z",
            "updatedAt": "2024-01-19T09:23:18.613Z"
        },
        {
            "id": 15682773,
            "tagId": 29535,
            "name": "mlb",
            "value": null,
            "labelerLogin": "cx@datasetninja.com",
            "createdAt": "2024-01-19T09:23:18.613Z",
            "updatedAt": "2024-01-19T09:23:18.613Z"
        },
        {
            "id": 15682774,
            "tagId": 29537,
            "name": "subcounty",
            "value": "Kamdini",
            "labelerLogin": "cx@datasetninja.com",
            "createdAt": "2024-01-19T09:23:18.613Z",
            "updatedAt": "2024-01-19T09:23:18.613Z"
        },
        {
            "id": 15682775,
            "tagId": 29538,
            "name": "variety",
            "value": "LOCAL",
            "labelerLogin": "cx@datasetninja.com",
            "createdAt": "2024-01-19T09:23:18.613Z",
            "updatedAt": "2024-01-19T09:23:18.613Z"
        }
    ],
    "size": {
        "height": 498,
        "width": 1024
    },
    "objects": [
        {
            "id": 128805712,
            "classId": 6511799,
            "objectId": null,
            "description": "",
            "geometryType": "rectangle",
            "labelerLogin": "cx@datasetninja.com",
            "createdAt": "2023-12-17T03:11:52.894Z",
            "updatedAt": "2023-12-17T03:11:52.894Z",
            "tags": [],
            "classTitle": "maize leaf blight",
            "points": {
                "exterior": [
                    [
                        3,
                        4
                    ],
                    [
                        1016,
                        489
                    ]
                ],
                "interior": []
            }
        }
    ]
}